taxi_simulator/__init__.py
taxi_simulator/cli.py
taxi_simulator/coordinator.py
taxi_simulator/helpers.py
taxi_simulator/passenger.py
taxi_simulator/protocol.py
taxi_simulator/route.py
taxi_simulator/scenario.py
taxi_simulator/simulator.py
taxi_simulator/strategies.py
taxi_simulator/strategies_fsm.py
taxi_simulator/taxi.py
taxi_simulator/utils.py
taxi_simulator/templates/index.html
taxi_simulator/templates/assets/css/app.css
taxi_simulator/templates/assets/css/bootstrap-treeview.min.css
taxi_simulator/templates/assets/img/favicon-120.png
taxi_simulator/templates/assets/img/favicon-152.png
taxi_simulator/templates/assets/img/favicon-196.png
taxi_simulator/templates/assets/img/favicon-76.png
taxi_simulator/templates/assets/img/favicon.ico
taxi_simulator/templates/assets/img/passenger.png
taxi_simulator/templates/assets/img/passenger2.png
taxi_simulator/templates/assets/img/taxi.png
taxi_simulator/templates/assets/img/taxi_busy.png
taxi_simulator/templates/assets/img/taxi_free.png
taxi_simulator/templates/assets/js/MovingMarker.js
taxi_simulator/templates/assets/js/SidebarComponent.vue
taxi_simulator/templates/assets/js/StatusIndicator.vue
taxi_simulator/templates/assets/js/TreeView.vue
taxi_simulator/templates/assets/js/app.js
taxi_simulator/templates/assets/js/app.js.old
taxi_simulator/templates/assets/js/main.js
taxi_simulator/templates/assets/js/package-lock.json
taxi_simulator/templates/assets/js/store.js
taxi_simulator/templates/assets/js/taxi.js
taxi_simulator/templates/assets/js/app/app.js
taxi_simulator/templates/assets/js/app/app.js.map
taxi_simulator/templates/assets/node_modules/coa/coverage/index.html
taxi_simulator/templates/assets/node_modules/coa/coverage/coa/index.html
taxi_simulator/templates/assets/node_modules/coa/coverage/coa/index.js.html
taxi_simulator/templates/assets/node_modules/coa/coverage/coa/lib/arg.js.html
taxi_simulator/templates/assets/node_modules/coa/coverage/coa/lib/cmd.js.html
taxi_simulator-0.4.1.dist-info/METADATA
taxi_simulator-0.4.1.dist-info/RECORD
taxi_simulator-0.4.1.dist-info/WHEEL
taxi_simulator-0.4.1.dist-info/entry_points.txt
taxi_simulator-0.4.1.dist-info/top_level.txt
