Metadata-Version: 2.1
Name: taxi-simulator
Version: 0.4.1
Summary: Agent-based taxi simulator to test strategies
Home-page: https://github.com/javipalanca/taxi_simulator
Author: Javi Palanca
Author-email: jpalanca@gmail.com
License: MIT license
Keywords: taxi_simulator
Platform: UNKNOWN
Classifier: Development Status :: 4 - Beta
Classifier: Intended Audience :: Developers
Classifier: Intended Audience :: Education
Classifier: Intended Audience :: Science/Research
Classifier: Topic :: Scientific/Engineering :: Artificial Intelligence
Classifier: License :: OSI Approved :: MIT License
Classifier: Natural Language :: English
Classifier: Programming Language :: Python :: 3
Classifier: Programming Language :: Python :: 3.6
Requires-Dist: Click (>=6.0)
Requires-Dist: spade (>=3.0.9)
Requires-Dist: pandas (==0.22.0)
Requires-Dist: tabulate (==0.8.2)
Requires-Dist: openpyxl (==2.4.9)
Requires-Dist: urllib3 (==1.22)
Requires-Dist: factory-boy (==2.11.1)
Requires-Dist: requests (==2.19.1)
Requires-Dist: geopy (==1.17.0)
Requires-Dist: XlsxWriter (==1.1.2)
